jobtty/__init__.py
jobtty/cli.py
jobtty/commands/__init__.py
jobtty/commands/ai.py
jobtty/commands/auth.py
jobtty/commands/challenges.py
jobtty/commands/companies.py
jobtty/commands/daemon.py
jobtty/commands/dashboard.py
jobtty/commands/git_commands.py
jobtty/commands/pair.py
jobtty/commands/payment.py
jobtty/commands/post.py
jobtty/commands/profile.py
jobtty/commands/recruit.py
jobtty/commands/search.py
jobtty/commands/searches.py
jobtty/commands/shell.py
jobtty/core/__init__.py
jobtty/core/ai_assistant.py
jobtty/core/api_client.py
jobtty/core/challenge_engine.py
jobtty/core/collaboration.py
jobtty/core/company_logos.py
jobtty/core/config.py
jobtty/core/display.py
jobtty/core/fallback_display.py
jobtty/core/git_integration.py
jobtty/core/notification_daemon.py
jobtty/core/saved_searches.py
jobtty/models/__init__.py
jobtty/models/challenge.py
jobtty/models/saved_search.py
jobtty/utils/__init__.py
jobtty-1.2.8.dist-info/METADATA
jobtty-1.2.8.dist-info/WHEEL
jobtty-1.2.8.dist-info/entry_points.txt
jobtty-1.2.8.dist-info/top_level.txt
jobtty-1.2.8.dist-info/RECORD
