Metadata-Version: 2.4
Name: jobtty
Version: 1.2.8
Summary: 🚀 Terminal Job Board - Find your next role from the command line
Home-page: https://github.com/croscomsoftware/jobtty
Author: Croscom Software
Author-email: Croscom Software <konrad@croscomsoftware.com>
Project-URL: Homepage, https://github.com/croscomsoftware/jobtty
Project-URL: Documentation, https://github.com/croscomsoftware/jobtty/blob/main/README.md
Project-URL: Repository, https://github.com/croscomsoftware/jobtty.git
Project-URL: Issues, https://github.com/croscomsoftware/jobtty/issues
Classifier: Development Status :: 5 - Production/Stable
Classifier: Intended Audience :: Developers
Classifier: License :: OSI Approved :: MIT License
Classifier: Operating System :: OS Independent
Classifier: Programming Language :: Python :: 3
Classifier: Programming Language :: Python :: 3.8
Classifier: Programming Language :: Python :: 3.9
Classifier: Programming Language :: Python :: 3.10
Classifier: Programming Language :: Python :: 3.11
Classifier: Programming Language :: Python :: 3.12
Classifier: Topic :: Internet :: WWW/HTTP
Classifier: Topic :: Office/Business
Classifier: Topic :: Software Development :: Libraries :: Python Modules
Requires-Python: >=3.8
Requires-Dist: click>=8.0.0
Requires-Dist: rich>=13.0.0
Requires-Dist: requests>=2.28.0
Requires-Dist: stripe>=5.0.0
Requires-Dist: keyring>=23.0.0
Requires-Dist: pydantic>=2.0.0
Requires-Dist: pydantic-settings>=2.0.0
Requires-Dist: qrcode[pil]>=7.0.0
Provides-Extra: git
Requires-Dist: GitPython>=3.1.0; extra == "git"
Provides-Extra: collaboration
Requires-Dist: websockets>=11.0.0; extra == "collaboration"
Provides-Extra: challenges
Requires-Dist: docker>=6.0.0; extra == "challenges"
Provides-Extra: dev
Requires-Dist: pytest>=7.0.0; extra == "dev"
Requires-Dist: pytest-cov>=4.0.0; extra == "dev"
Requires-Dist: pytest-mock>=3.10.0; extra == "dev"
Requires-Dist: black>=23.0.0; extra == "dev"
Requires-Dist: flake8>=6.0.0; extra == "dev"
Requires-Dist: mypy>=1.0.0; extra == "dev"
Requires-Dist: pre-commit>=3.0.0; extra == "dev"
Provides-Extra: test
Requires-Dist: pytest>=7.0.0; extra == "test"
Requires-Dist: pytest-cov>=4.0.0; extra == "test"
Requires-Dist: pytest-mock>=3.10.0; extra == "test"
Provides-Extra: all
Requires-Dist: GitPython>=3.1.0; extra == "all"
Requires-Dist: websockets>=11.0.0; extra == "all"
Requires-Dist: docker>=6.0.0; extra == "all"
Dynamic: author
Dynamic: home-page
Dynamic: requires-python
